{"render_as":"table","series":{"metadata":{"DEMONHUNTER":{},"DRUID":{},"HUNTER":{},"MAGE":{},"PALADIN":{},"PRIEST":{},"ROGUE":{},"SHAMAN":{},"WARLOCK":{},"WARRIOR":{}},"data":{"DEMONHUNTER":[{"shortid":"8l5yubLAOU4gXXO3aImqOh","deck_list":"[[61127,2],[56583,2],[59726,2],[57732,1],[61939,2],[57193,2],[906,2],[749,1],[59869,2],[58201,2],[59606,2],[56791,2],[58453,2],[58183,2],[57184,2],[61136,1],[56765,1]]","archetype_id":424,"popularity_delta":4.71,"total_games":2126,"win_rate":53.67,"avg_game_length_seconds":484,"avg_num_player_turns":8.5},{"shortid":"Fcru5YrZbX3g3pMjstjbkf","deck_list":"[[61127,2],[56583,2],[58452,1],[59726,2],[57732,1],[61939,2],[57193,2],[906,1],[749,1],[59869,2],[58201,2],[59606,2],[56791,2],[58453,2],[58183,2],[57184,2],[61136,1],[56765,1]]","archetype_id":424,"popularity_delta":4.01,"total_games":3155,"win_rate":52.09,"avg_game_length_seconds":480,"avg_num_player_turns":8.5},{"shortid":"zx3oqTdpYeRHgRE5Xpp7Dh","deck_list":"[[61132,2],[56583,2],[58452,2],[59724,2],[56928,2],[59259,2],[58492,2],[59732,2],[59646,2],[58201,2],[59089,2],[56791,2],[59725,2],[61125,2],[60151,2]]","archetype_id":397,"popularity_delta":1.06,"total_games":866,"win_rate":56.85,"avg_game_length_seconds":469,"avg_num_player_turns":8.5}],"DRUID":[{"shortid":"dyzRgg1GxMQ00I5OPgitgb","deck_list":"[[61450,2],[254,2],[381,2],[55039,1],[55031,1],[56680,2],[56057,1],[59542,2],[60016,2],[493,2],[61964,2],[56677,2],[59163,2],[55036,2],[61449,2],[742,1],[56687,2]]","archetype_id":372,"popularity_delta":4.77,"total_games":4152,"win_rate":55.95,"avg_game_length_seconds":381,"avg_num_player_turns":7},{"shortid":"Ln4bqr7rHVUSKYWAQbwyEe","deck_list":"[[61450,1],[254,2],[1124,1],[51769,2],[56680,2],[55030,1],[60016,2],[61964,2],[53218,2],[56686,2],[56677,2],[53979,2],[56684,2],[59163,2],[61449,2],[742,1],[56687,2]]","archetype_id":372,"popularity_delta":1.1,"total_games":537,"win_rate":54.24,"avg_game_length_seconds":418,"avg_num_player_turns":7.5},{"shortid":"FEOrdx9f9c72kgBnlGBBe","deck_list":"[[59029,2],[254,2],[61670,2],[1124,1],[51769,1],[56680,2],[55030,1],[60016,2],[53615,2],[59539,2],[59026,1],[61649,1],[59450,2],[53979,1],[59614,2],[60926,2],[59163,2],[59452,2]]","archetype_id":398,"popularity_delta":0.78,"total_games":806,"win_rate":56.61,"avg_game_length_seconds":436,"avg_num_player_turns":8.5},{"shortid":"tagMfQhsGTHRwGikci1IIe","deck_list":"[[51779,2],[61450,2],[381,2],[55039,2],[52810,2],[53551,2],[59705,2],[56057,2],[503,2],[60016,2],[61964,2],[56677,2],[59163,2],[742,2],[56687,2]]","archetype_id":372,"popularity_delta":0.78,"total_games":3317,"win_rate":57.86,"avg_game_length_seconds":345,"avg_num_player_turns":6.5}],"HUNTER":[{"shortid":"KQyAlP005Le0AMYQ3HHGXd","deck_list":"[[58972,1],[55161,1],[60278,1],[53926,1],[61898,1],[61683,1],[296,1],[56703,1],[1243,1],[59035,1],[519,1],[59705,1],[437,1],[59170,1],[55291,1],[61682,1],[56482,1],[59394,1],[57175,1],[59590,1],[1662,1],[61672,1],[61839,1],[53756,1],[57182,1],[61700,1],[56484,1],[55303,1],[455,1],[55292,1]]","archetype_id":302,"popularity_delta":2,"total_games":5192,"win_rate":59.27,"avg_game_length_seconds":385,"avg_num_player_turns":7.5},{"shortid":"lqzucqk1xeZITWsAesx94c","deck_list":"[[55301,1],[60278,1],[296,2],[56703,2],[59035,2],[519,1],[59705,2],[59170,2],[55291,2],[585,1],[56482,2],[59394,2],[59590,2],[1662,2],[55303,1],[55292,2],[53919,1],[58972,2]]","archetype_id":355,"popularity_delta":1.29,"total_games":3005,"win_rate":59.57,"avg_game_length_seconds":360,"avg_num_player_turns":7},{"shortid":"TTrzaDIh7TejVFqpK3Rd5","deck_list":"[[58972,1],[55161,1],[60278,1],[53926,1],[61898,1],[296,1],[56703,1],[1243,1],[59035,1],[519,1],[59705,1],[437,1],[59170,1],[55291,1],[61702,1],[61682,1],[585,1],[56482,1],[59394,1],[59590,1],[1662,1],[61672,1],[61839,1],[53756,1],[57182,1],[56484,1],[61700,1],[55303,1],[455,1],[55292,1]]","archetype_id":302,"popularity_delta":0.61,"total_games":629,"win_rate":60.49,"avg_game_length_seconds":392,"avg_num_player_turns":7.5}],"MAGE":[{"shortid":"tVtyquZMyjdsgLrkmUv8zd","deck_list":"[[1084,2],[56385,2],[61957,2],[58770,1],[662,2],[564,2],[614,2],[59207,2],[59213,2],[52639,2],[52991,2],[555,2],[59639,2],[932,2],[56389,1],[58976,2]]","archetype_id":431,"popularity_delta":0.92,"total_games":1934,"win_rate":44.42,"avg_game_length_seconds":430,"avg_num_player_turns":7.5},{"shortid":"r0OgogYZaVIm5pU0CpzNXg","deck_list":"[[1084,2],[56385,2],[61957,2],[58770,1],[662,2],[564,2],[614,2],[59207,1],[59213,2],[54906,1],[52639,2],[52991,2],[555,2],[59639,2],[932,2],[56389,1],[58976,2]]","archetype_id":431,"popularity_delta":0.74,"total_games":647,"win_rate":48,"avg_game_length_seconds":394,"avg_num_player_turns":7.5},{"shortid":"PUpQWk3vy4n96NeWqOB5Qf","deck_list":"[[59216,1],[56439,2],[662,2],[749,1],[59013,2],[564,2],[61959,2],[59213,2],[61956,1],[54901,2],[54906,2],[59639,2],[54907,2],[56161,1],[59556,2],[59621,1],[56717,1],[52289,2]]","archetype_id":391,"popularity_delta":0.58,"total_games":570,"win_rate":54.39,"avg_game_length_seconds":503,"avg_num_player_turns":9}],"PALADIN":[{"shortid":"Tbcndi59C7z10oArdCauw","deck_list":"[[59594,2],[57476,1],[55067,1],[59587,1],[56445,2],[56394,2],[56554,2],[59038,2],[59583,1],[476,2],[55068,2],[61192,1],[61949,2],[56444,1],[56555,2],[56556,2],[57546,2],[56077,2]]","archetype_id":338,"popularity_delta":1.29,"total_games":2767,"win_rate":60.12,"avg_game_length_seconds":465,"avg_num_player_turns":8.5},{"shortid":"hFSFzXtHgZFAZZ2s8vU3Jg","deck_list":"[[57476,1],[59029,2],[56445,2],[59039,2],[56394,2],[56554,2],[59038,2],[61949,1],[56444,1],[1373,2],[61947,2],[56555,2],[56556,2],[57546,2],[54037,2],[59584,2],[59411,1]]","archetype_id":411,"popularity_delta":1.19,"total_games":749,"win_rate":56.25,"avg_game_length_seconds":562,"avg_num_player_turns":9.5},{"shortid":"HHY3y1k8PxXpyxDIAyiI4d","deck_list":"[[61305,2],[57476,1],[59594,2],[55067,1],[59587,1],[56445,2],[56394,1],[56554,2],[59038,2],[55068,2],[61192,1],[61949,2],[56555,2],[56556,2],[57546,2],[55048,2],[59584,2],[56077,1]]","archetype_id":338,"popularity_delta":0.65,"total_games":668,"win_rate":55.75,"avg_game_length_seconds":504,"avg_num_player_turns":9}],"PRIEST":[{"shortid":"NxjQLL9Z5qhRHTCaYceqCe","deck_list":"[[56088,2],[61282,2],[61944,2],[58791,2],[56623,2],[56595,2],[53932,2],[56603,2],[61642,2],[279,2],[58974,2],[61947,2],[55425,2],[61435,2],[59223,2]]","archetype_id":36,"popularity_delta":1.35,"total_games":581,"win_rate":44.22,"avg_game_length_seconds":577,"avg_num_player_turns":9.5},{"shortid":"qRL7pr1kDR4RVpoNgXZlme","deck_list":"[[61685,2],[61945,1],[61282,2],[61437,1],[61944,2],[61670,2],[56595,2],[61308,1],[57160,1],[54873,2],[60979,2],[61283,2],[57416,1],[61674,2],[61435,2],[61268,2],[55438,1],[61639,2]]","archetype_id":432,"popularity_delta":0.65,"total_games":882,"win_rate":45.88,"avg_game_length_seconds":552,"avg_num_player_turns":10},{"shortid":"TpYUX4xKyJgHJjJXblYJCd","deck_list":"[[61282,2],[61434,2],[52627,1],[51714,2],[56595,2],[57160,1],[1363,1],[52438,1],[54898,2],[53409,2],[57416,1],[52633,2],[54425,2],[61436,1],[61435,2],[59083,2],[54431,2],[841,2]]","archetype_id":129,"popularity_delta":0.18,"total_games":323,"win_rate":53.72,"avg_game_length_seconds":650,"avg_num_player_turns":12.5}],"ROGUE":[{"shortid":"fd9VyRb1d0QoYzxxI0iszd","deck_list":"[[56377,2],[59609,1],[180,2],[56527,2],[59914,2],[59989,2],[59690,1],[61953,2],[59403,2],[459,2],[59400,2],[58794,2],[60023,2],[878,2],[904,2],[994,2]]","archetype_id":408,"popularity_delta":3.55,"total_games":11291,"win_rate":59.92,"avg_game_length_seconds":343,"avg_num_player_turns":6.5},{"shortid":"U3RFEcbec6fPExr9rTLZqf","deck_list":"[[56377,2],[180,1],[61159,2],[56527,2],[59914,2],[724,2],[61151,2],[61953,2],[54015,2],[58794,2],[57177,1],[56378,2],[710,2],[54426,1],[268,1],[904,2],[994,2]]","archetype_id":172,"popularity_delta":1.18,"total_games":993,"win_rate":58.99,"avg_game_length_seconds":309,"avg_num_player_turns":6},{"shortid":"RLdsvlzvO2tez7hfQUghkg","deck_list":"[[56524,2],[61954,2],[59609,1],[180,2],[61159,2],[57979,1],[59877,1],[54261,2],[61151,2],[61953,2],[58794,2],[57145,1],[52111,2],[56528,2],[59556,2],[904,2],[56526,2]]","archetype_id":375,"popularity_delta":0.57,"total_games":1193,"win_rate":59.14,"avg_game_length_seconds":524,"avg_num_player_turns":8.5}],"SHAMAN":[{"shortid":"5ch38MMcg5yHlj0Azsfoqd","deck_list":"[[56411,2],[864,2],[59216,1],[52654,2],[58977,2],[59576,2],[61226,1],[56420,1],[59164,1],[61223,2],[749,1],[61959,2],[59213,2],[61961,2],[58790,2],[505,2],[57184,2],[52289,1]]","archetype_id":406,"popularity_delta":1.86,"total_games":623,"win_rate":51.68,"avg_game_length_seconds":414,"avg_num_player_turns":8},{"shortid":"iE3zlquJ96C1YNSozeNKsg","deck_list":"[[55426,1],[59029,2],[60892,2],[54488,2],[59035,2],[61226,2],[61225,2],[56413,2],[60016,2],[284,2],[211,1],[55400,2],[878,2],[52422,2],[61222,1],[56417,1],[53972,2]]","archetype_id":202,"popularity_delta":0.89,"total_games":537,"win_rate":57.72,"avg_game_length_seconds":397,"avg_num_player_turns":7.5},{"shortid":"y0sut1PpTPzFFsGlhizClg","deck_list":"[[56411,2],[61227,2],[54009,2],[54966,2],[61226,2],[56470,2],[59164,1],[513,2],[57177,2],[53990,1],[61961,2],[52422,2],[54965,2],[59558,1],[51,2],[61960,2],[61973,1]]","archetype_id":201,"popularity_delta":0.33,"total_games":328,"win_rate":55.09,"avg_game_length_seconds":377,"avg_num_player_turns":7.5}],"WARLOCK":[{"shortid":"qAPg45VV2RjNe0cPjdegv","deck_list":"[[1090,2],[61203,2],[59029,2],[59724,2],[61898,2],[56534,1],[59035,2],[48,2],[56523,2],[59585,2],[61648,2],[974,2],[56502,2],[59223,2],[53885,1],[56501,2]]","archetype_id":134,"popularity_delta":0.84,"total_games":3056,"win_rate":57.96,"avg_game_length_seconds":367,"avg_num_player_turns":6.5},{"shortid":"HnikHhdwnKfVtgJDNLLryg","deck_list":"[[1090,2],[61203,2],[59724,2],[61898,2],[56534,1],[59035,2],[48,2],[61207,2],[56523,2],[59585,2],[61648,2],[974,2],[56502,2],[59223,2],[56501,2],[53885,1]]","archetype_id":134,"popularity_delta":0.6,"total_games":1756,"win_rate":58.49,"avg_game_length_seconds":343,"avg_num_player_turns":6.5},{"shortid":"Xr61kUYPnk2UZtFfb2sDPe","deck_list":"[[1090,2],[61203,1],[59029,2],[59724,2],[61898,2],[56534,1],[59035,2],[48,2],[56523,2],[61942,1],[59585,2],[61648,2],[974,2],[56502,2],[59223,2],[56501,2],[53885,1]]","archetype_id":134,"popularity_delta":0.45,"total_games":1276,"win_rate":55.64,"avg_game_length_seconds":383,"avg_num_player_turns":7}],"WARRIOR":[{"shortid":"xhN5O481q43RMjerBLgIQf","deck_list":"[[55005,2],[338,1],[54492,2],[22,2],[58979,1],[61237,2],[28,1],[56507,2],[56732,2],[56107,2],[56512,1],[400,2],[60023,2],[59409,2],[55006,1],[56100,2],[59411,1],[596,2]]","archetype_id":161,"popularity_delta":0.66,"total_games":601,"win_rate":56,"avg_game_length_seconds":481,"avg_num_player_turns":8.5},{"shortid":"o8mvrcnX0an9xV2lA5m1qh","deck_list":"[[1023,2],[55907,1],[55001,2],[55007,1],[59690,1],[56504,2],[57718,2],[51738,2],[56512,2],[75,2],[55400,1],[61238,2],[60023,2],[546,2],[59402,1],[59411,1],[51739,1],[511,2],[57413,1]]","archetype_id":290,"popularity_delta":0.57,"total_games":1484,"win_rate":55.63,"avg_game_length_seconds":504,"avg_num_player_turns":10},{"shortid":"LZmuWr4hLmlNl7HbGrOU1f","deck_list":"[[1023,2],[55907,1],[55001,2],[55007,1],[59690,1],[56504,1],[57718,2],[51738,2],[56512,2],[75,2],[55400,2],[61238,2],[60023,2],[546,2],[59402,1],[59411,1],[51739,1],[511,2],[57413,1]]","archetype_id":290,"popularity_delta":0.41,"total_games":899,"win_rate":55.58,"avg_game_length_seconds":506,"avg_num_player_turns":10}]}},"as_of":"2021-01-25T08:54:33Z"}