{"render_as":"table","series":{"metadata":{"DRUID":{},"HUNTER":{},"MAGE":{},"PALADIN":{},"PRIEST":{},"ROGUE":{},"SHAMAN":{},"WARLOCK":{},"WARRIOR":{}},"data":{"DRUID":[{"shortid":"GCZ7SPFo4C1LfFcjauvYE","deck_list":"[[43417,1],[40596,1],[42656,2],[45828,2],[47423,2],[40372,2],[1802,2],[233,2],[52438,1],[42759,2],[43294,2],[40797,2],[64,2],[40523,2],[43284,2],[86,1],[43288,2]]","archetype_id":null,"popularity_delta":0.45,"total_games":118,"win_rate":61.59,"avg_game_length_seconds":624,"avg_num_player_turns":12},{"shortid":"h4sQoXgy1EgYb9quNtyJHh","deck_list":"[[43417,1],[40596,1],[42656,2],[45828,2],[47423,2],[40372,2],[1802,1],[52438,1],[42759,2],[95,2],[40797,2],[43294,2],[64,2],[40523,2],[52307,2],[51733,2],[43288,2]]","archetype_id":null,"popularity_delta":0.42,"total_games":33,"win_rate":58.55,"avg_game_length_seconds":597,"avg_num_player_turns":11}],"HUNTER":[{"shortid":"wSquELzktMhYgVGx1iiWv","deck_list":"[[49184,1],[41304,2],[46390,1],[1721,1],[1243,1],[45537,2],[41259,1],[47488,1],[52082,2],[47346,2],[42652,2],[46461,1],[1786,2],[2044,2],[43398,1],[45195,2],[1047,1],[48185,1],[41286,1],[43357,2],[1991,1]]","archetype_id":null,"popularity_delta":0.56,"total_games":33,"win_rate":55.02,"avg_game_length_seconds":475,"avg_num_player_turns":9.5},{"shortid":"uSE63ifzNiEKco7fo3hSAh","deck_list":"[[48886,2],[48025,1],[48536,2],[1932,2],[49184,1],[52790,1],[45537,1],[56223,1],[48529,1],[1940,2],[48983,2],[2062,2],[47842,2],[2016,2],[49161,2],[2260,1],[2052,2],[2075,1],[49356,2]]","archetype_id":null,"popularity_delta":0.42,"total_games":25,"win_rate":63.91,"avg_game_length_seconds":304,"avg_num_player_turns":6.5},{"shortid":"KFlaJ6dZCAW21SGDmug1Ld","deck_list":"[[699,2],[48201,1],[296,2],[40426,2],[1243,2],[437,2],[49824,2],[606,1],[43398,1],[1047,2],[50212,2],[2260,2],[39481,2],[1281,2],[41358,2],[43357,2],[45707,1]]","archetype_id":null,"popularity_delta":0.27,"total_games":15,"win_rate":62.37,"avg_game_length_seconds":390,"avg_num_player_turns":8}],"MAGE":[{"shortid":"3y9GNQS5hEy64mFm1uBBuf","deck_list":"[[1801,2],[39767,2],[54493,2],[47982,1],[315,2],[43407,2],[53822,2],[41153,2],[113,2],[43426,1],[40583,2],[54772,2],[1783,2],[40299,2],[53823,2],[748,2]]","archetype_id":null,"popularity_delta":2.79,"total_games":1064,"win_rate":71.55,"avg_game_length_seconds":351,"avg_num_player_turns":8},{"shortid":"7dBOgCIIHISYNrR2wAPtze","deck_list":"[[1016,2],[138,2],[457,2],[1080,1],[2262,1],[621,1],[284,2],[41153,1],[430,1],[45590,2],[614,2],[48692,2],[1783,2],[587,2],[43193,1],[555,2],[41690,2],[192,2]]","archetype_id":null,"popularity_delta":0.1,"total_games":19,"win_rate":56.21,"avg_game_length_seconds":495,"avg_num_player_turns":10},{"shortid":"mPdvpxxr6MCvHgIIEaJAk","deck_list":"[[50120,2],[41168,1],[47982,1],[52706,2],[662,2],[749,1],[52438,1],[39426,2],[49081,2],[172,2],[614,2],[2275,2],[48692,2],[52639,2],[52991,2],[555,2],[41496,2]]","archetype_id":null,"popularity_delta":0.08,"total_games":16,"win_rate":56.33,"avg_game_length_seconds":451,"avg_num_player_turns":8.5}],"PALADIN":[{"shortid":"ESwlYnpuCA8sG0TbgxNoVb","deck_list":"[[48993,2],[679,2],[49184,1],[47775,2],[56223,1],[1940,2],[48983,2],[48985,2],[53445,2],[48982,2],[40567,2],[2052,2],[40371,2],[48989,2],[49356,2],[2026,2]]","archetype_id":null,"popularity_delta":1.47,"total_games":167,"win_rate":61.35,"avg_game_length_seconds":328,"avg_num_player_turns":7},{"shortid":"uzaOVtotXfMmwVkjnn1cOe","deck_list":"[[679,2],[38911,2],[2029,2],[38745,1],[52494,2],[49018,1],[559,1],[70,2],[41859,1],[43515,2],[2028,2],[290,1],[48982,2],[45265,2],[2717,2],[42467,2],[48158,1],[41912,2]]","archetype_id":null,"popularity_delta":0.58,"total_games":49,"win_rate":66.41,"avg_game_length_seconds":346,"avg_num_player_turns":7.5},{"shortid":"djBFkTLYTItD3LTFaisMmc","deck_list":"[[679,2],[38911,2],[2029,2],[38745,1],[52494,2],[559,1],[70,2],[724,2],[41859,1],[45782,1],[43515,1],[2028,2],[290,1],[1914,1],[2717,1],[42467,2],[48158,1],[40465,1],[2515,2],[41912,2]]","archetype_id":null,"popularity_delta":0.41,"total_games":39,"win_rate":64.56,"avg_game_length_seconds":350,"avg_num_player_turns":7}],"PRIEST":[{"shortid":"3ZSfRlPp1qCE8OuB5gFkKg","deck_list":"[[40432,1],[41169,2],[50408,1],[40378,2],[40373,2],[39554,2],[41176,2],[45899,2],[1790,2],[376,2],[1361,2],[2286,2],[613,2],[1366,1],[46460,1],[48101,2],[1650,2]]","archetype_id":null,"popularity_delta":0.33,"total_games":34,"win_rate":59.97,"avg_game_length_seconds":409,"avg_num_player_turns":8},{"shortid":"i3MVxkIuGqLpMz2Use5P9d","deck_list":"[[50071,2],[2298,2],[39941,1],[41169,2],[52627,1],[42598,2],[1938,1],[1363,1],[52438,1],[43112,2],[52633,1],[1367,2],[42992,2],[38312,1],[42818,1],[46307,2],[40375,2],[42597,2],[42804,2]]","archetype_id":null,"popularity_delta":0.3,"total_games":87,"win_rate":61.42,"avg_game_length_seconds":474,"avg_num_player_turns":10.5},{"shortid":"dg0z0nnqTkKpLSW0b4KaFh","deck_list":"[[50071,2],[2298,2],[39941,1],[41169,2],[52632,1],[52627,1],[42598,2],[1938,1],[1363,1],[52438,1],[43112,2],[52633,1],[1367,1],[42992,2],[42818,1],[38312,1],[46307,2],[40375,2],[42597,2],[42804,2]]","archetype_id":null,"popularity_delta":0.28,"total_games":170,"win_rate":60.45,"avg_game_length_seconds":474,"avg_num_player_turns":10.5}],"ROGUE":[{"shortid":"Strzgnw5ykGG180cS4ZdGb","deck_list":"[[52617,2],[43237,2],[180,2],[48487,1],[559,1],[724,2],[459,2],[461,2],[2043,2],[680,2],[878,2],[2715,2],[456,1],[52111,2],[40465,1],[904,2],[39698,2]]","archetype_id":null,"popularity_delta":0.21,"total_games":15,"win_rate":60.24,"avg_game_length_seconds":337,"avg_num_player_turns":7},{"shortid":"5vOfL1CtjBPaSzPjzP6fCd","deck_list":"[[43237,2],[1988,2],[40889,2],[48487,1],[47035,1],[2095,2],[724,2],[459,2],[461,2],[2043,2],[878,2],[2715,2],[456,1],[1158,2],[50773,2],[40465,1],[904,2]]","archetype_id":null,"popularity_delta":0.18,"total_games":22,"win_rate":57.67,"avg_game_length_seconds":317,"avg_num_player_turns":7},{"shortid":"OenuOB7lPnzzK669oOWXUd","deck_list":"[[49184,1],[56223,1],[559,1],[724,2],[2291,2],[41323,2],[43515,2],[47014,2],[1914,1],[680,2],[45265,2],[2715,2],[52111,2],[1117,2],[41217,2],[48158,1],[40465,1],[39698,2]]","archetype_id":null,"popularity_delta":0.1,"total_games":7,"win_rate":64.74,"avg_game_length_seconds":381,"avg_num_player_turns":7.5}],"SHAMAN":[{"shortid":"EVimsgnT6IisLBxV7QEAee","deck_list":"[[40596,1],[48161,1],[40455,2],[374,1],[40694,2],[38263,2],[211,2],[38267,2],[51,1],[2613,2],[48527,2],[40529,2],[2006,2],[46996,2],[42818,1],[47693,1],[39712,2],[2610,2]]","archetype_id":null,"popularity_delta":0.31,"total_games":31,"win_rate":59.8,"avg_game_length_seconds":411,"avg_num_player_turns":8.5},{"shortid":"sgX0WDyNEBnKnWJ0LuXFpd","deck_list":"[[40419,2],[453,2],[52277,2],[41265,2],[475,2],[2948,1],[13879,2],[40694,2],[1063,2],[736,1],[41245,2],[1914,1],[51724,2],[3007,2],[42678,2],[39712,1],[40803,1],[41478,1]]","archetype_id":null,"popularity_delta":0.1,"total_games":12,"win_rate":64.77,"avg_game_length_seconds":303,"avg_num_player_turns":6.5},{"shortid":"KoqnE2HTjEsFkQ4lxwM2me","deck_list":"[[40596,1],[40455,2],[2290,2],[40694,2],[38263,2],[211,2],[38267,2],[48527,2],[40529,2],[47222,2],[2006,2],[50550,2],[46996,2],[39712,2],[47693,1],[2610,2]]","archetype_id":null,"popularity_delta":0.07,"total_games":12,"win_rate":61.64,"avg_game_length_seconds":391,"avg_num_player_turns":8}],"WARLOCK":[{"shortid":"ovdd6E64MHKHKFAGw3UoFe","deck_list":"[[41885,1],[42784,1],[138,2],[49184,1],[42565,1],[2262,1],[43415,1],[2883,1],[48625,1],[41872,2],[46056,2],[46286,1],[43122,2],[860,2],[1806,2],[42471,2],[41566,2],[48156,1],[163,1],[859,1],[1092,2]]","archetype_id":null,"popularity_delta":0.61,"total_games":107,"win_rate":56.19,"avg_game_length_seconds":499,"avg_num_player_turns":10.5},{"shortid":"65G0xxTH2VCNQD5SDr30Ue","deck_list":"[[41885,1],[49423,1],[49184,1],[2262,1],[43415,1],[48625,1],[41872,2],[1986,1],[46056,2],[46286,1],[43122,2],[38770,1],[860,2],[1806,2],[2037,2],[42471,2],[41566,2],[48156,1],[163,2],[1092,2]]","archetype_id":null,"popularity_delta":0.38,"total_games":40,"win_rate":56.69,"avg_game_length_seconds":461,"avg_num_player_turns":9.5},{"shortid":"OjEWr6IuXP4u2CE0PpMJzc","deck_list":"[[42784,1],[2093,1],[38496,1],[1657,1],[138,1],[41567,1],[49184,1],[42743,1],[2262,1],[41871,1],[43415,1],[2883,1],[1986,1],[46056,1],[43122,1],[46403,1],[40408,1],[1806,1],[42471,1],[41566,1],[914,1],[47557,1],[950,1],[48156,1],[48039,1],[53756,1],[859,1],[2949,1],[42670,1],[1100,1]]","archetype_id":null,"popularity_delta":0.17,"total_games":47,"win_rate":54.28,"avg_game_length_seconds":592,"avg_num_player_turns":12.5}],"WARRIOR":[{"shortid":"grWpPsVJzAnDuh2g6g6WSh","deck_list":"[[1805,2],[2948,1],[28,2],[38914,2],[35025,1],[559,1],[50410,2],[724,2],[1007,2],[2043,2],[680,2],[38920,2],[878,2],[999,2],[654,2],[40465,1],[511,2]]","archetype_id":null,"popularity_delta":0.24,"total_games":41,"win_rate":58.88,"avg_game_length_seconds":262,"avg_num_player_turns":6},{"shortid":"wTuFORkxtCCSJktRVgQGff","deck_list":"[[1657,1],[1016,2],[49184,1],[1023,2],[48515,1],[48691,2],[41243,2],[1790,2],[38530,2],[2729,2],[48146,1],[75,2],[48526,1],[546,2],[48158,1],[2949,1],[1793,1],[46026,2],[48542,2]]","archetype_id":null,"popularity_delta":0.13,"total_games":9,"win_rate":51.58,"avg_game_length_seconds":627,"avg_num_player_turns":13},{"shortid":"fy3XJ5qWzWk6c0ovqxc1Af","deck_list":"[[47825,2],[51735,2],[49184,1],[47511,2],[48753,2],[48691,2],[46650,1],[53251,2],[47133,2],[50074,1],[51738,2],[48146,1],[52242,1],[48526,1],[47053,1],[52288,1],[47131,1],[51739,1],[49269,2],[48542,2]]","archetype_id":290,"popularity_delta":0.07,"total_games":7,"win_rate":47.85,"avg_game_length_seconds":628,"avg_num_player_turns":12}]}},"as_of":"2019-08-15T11:15:59Z"}