{"render_as":"table","series":{"metadata":{"DEMONHUNTER":{},"DRUID":{},"HUNTER":{},"MAGE":{},"PALADIN":{},"PRIEST":{},"ROGUE":{},"SHAMAN":{},"WARLOCK":{},"WARRIOR":{}},"data":{"DEMONHUNTER":[{"shortid":"fpF80QsMpDGMux3iApJuNb","deck_list":"[[61127,2],[64720,1],[61939,2],[60153,2],[57193,2],[62485,2],[69684,2],[59869,2],[63229,2],[59606,2],[64394,2],[64709,2],[69740,2],[61273,2],[64395,1],[61136,1],[64375,1]]","archetype_id":473,"popularity_delta":2.07,"total_games":1099,"win_rate":44.33,"avg_game_length_seconds":505,"avg_num_player_turns":8},{"shortid":"mPTdZsBqFpuXPMhPumADIh","deck_list":"[[61127,2],[61939,2],[57193,2],[62485,2],[63682,2],[59869,2],[69558,2],[69507,2],[58201,2],[59606,2],[64397,1],[64394,2],[61125,2],[69740,2],[64393,2],[61136,1]]","archetype_id":430,"popularity_delta":0.78,"total_games":263,"win_rate":48.03,"avg_game_length_seconds":477,"avg_num_player_turns":8.5},{"shortid":"GxB1y7mj4GPb7vcnvgzQSb","deck_list":"[[61127,2],[61939,2],[60153,2],[62485,2],[69684,2],[63682,2],[59869,2],[69558,2],[69507,2],[59606,1],[64397,1],[64394,2],[58549,1],[64709,2],[61273,2],[64393,2],[64375,1]]","archetype_id":430,"popularity_delta":0.71,"total_games":990,"win_rate":43.1,"avg_game_length_seconds":540,"avg_num_player_turns":8.5}],"DRUID":[{"shortid":"CuXqSI9FQLkollIHsRyWCg","deck_list":"[[62583,2],[64388,2],[59705,2],[64201,2],[64372,2],[64385,2],[57175,2],[69718,2],[61964,2],[64008,2],[61606,1],[59026,2],[64337,2],[57182,2],[63033,2],[69653,1]]","archetype_id":52,"popularity_delta":1.06,"total_games":17007,"win_rate":61.76,"avg_game_length_seconds":381,"avg_num_player_turns":7},{"shortid":"s53R2xxJZn2QHQWsHJUjRh","deck_list":"[[62583,2],[61898,2],[64388,2],[59705,2],[64201,2],[64372,2],[64385,2],[57175,2],[69718,2],[61964,2],[64008,2],[61606,1],[59026,2],[62588,1],[57182,2],[63033,2]]","archetype_id":52,"popularity_delta":0.51,"total_games":3650,"win_rate":62.46,"avg_game_length_seconds":386,"avg_num_player_turns":7},{"shortid":"egBt685vcC1XRetIcP7Due","deck_list":"[[62583,2],[64388,2],[59705,2],[64201,2],[64372,2],[64385,2],[57175,2],[69718,2],[61964,2],[64008,2],[59026,2],[64337,2],[57182,2],[63033,2],[69653,2]]","archetype_id":52,"popularity_delta":0.24,"total_games":272,"win_rate":59.95,"avg_game_length_seconds":364,"avg_num_player_turns":7}],"HUNTER":[{"shortid":"qwndS58PXy1OYG0I1wLxXe","deck_list":"[[58972,2],[62812,1],[63591,1],[69691,2],[59705,2],[59170,2],[63088,2],[61702,2],[56482,2],[59394,2],[57175,2],[64631,2],[61839,1],[57182,2],[61973,1],[59233,1],[60043,2],[63461,1]]","archetype_id":355,"popularity_delta":1.08,"total_games":496,"win_rate":56.17,"avg_game_length_seconds":345,"avg_num_player_turns":7},{"shortid":"NhtehVUlJkf13ge299f49e","deck_list":"[[59457,1],[56703,2],[62698,2],[64964,2],[69545,2],[59170,2],[63088,2],[61702,2],[63007,2],[61846,1],[64008,2],[59449,2],[69693,2],[63195,2],[64712,2],[65044,2]]","archetype_id":170,"popularity_delta":0.64,"total_games":563,"win_rate":51.35,"avg_game_length_seconds":429,"avg_num_player_turns":8},{"shortid":"Fhh188iUDfiPda928XUlnd","deck_list":"[[62812,2],[59259,2],[63591,1],[69655,1],[69691,2],[69545,2],[60004,1],[62486,2],[59646,2],[69546,2],[59449,2],[64631,2],[63195,2],[64637,1],[61839,1],[61965,2],[65044,2],[63461,1]]","archetype_id":211,"popularity_delta":0.6,"total_games":1003,"win_rate":53.98,"avg_game_length_seconds":459,"avg_num_player_turns":8}],"MAGE":[{"shortid":"jfu9kCu7ilBkIbepHMfald","deck_list":"[[64430,2],[69500,2],[56385,2],[63057,2],[64488,1],[63056,2],[69608,2],[64423,2],[59207,2],[59213,2],[69501,2],[59639,2],[59556,2],[62804,2],[64434,2],[65140,1]]","archetype_id":142,"popularity_delta":1.13,"total_games":12449,"win_rate":55.4,"avg_game_length_seconds":502,"avg_num_player_turns":8},{"shortid":"gkiLC8k7Ba6ncUc1dqzC8c","deck_list":"[[64430,2],[69500,2],[56385,2],[63057,2],[64488,1],[63056,2],[69608,2],[64423,2],[59207,2],[59213,2],[69501,2],[59639,2],[59556,1],[62804,2],[58976,1],[64434,2],[65140,1]]","archetype_id":142,"popularity_delta":0.6,"total_games":2141,"win_rate":55.92,"avg_game_length_seconds":493,"avg_num_player_turns":8},{"shortid":"b7DwpLWAvgnsErL2jCCksc","deck_list":"[[64430,2],[57217,2],[61291,2],[69500,2],[56385,2],[63057,2],[64488,1],[63056,2],[69608,1],[64423,2],[59207,2],[69606,1],[59213,2],[69501,2],[59639,2],[62804,1],[64434,2]]","archetype_id":142,"popularity_delta":0.46,"total_games":1832,"win_rate":53.85,"avg_game_length_seconds":497,"avg_num_player_turns":8.5}],"PALADIN":[{"shortid":"I96pwrQ1Kpz3FeNBsFnNfd","deck_list":"[[66856,1],[69705,2],[64711,1],[66858,1],[64546,1],[64729,1],[64554,1],[59601,2],[62947,2],[56444,1],[64008,2],[57546,2],[64371,2],[62993,1],[62924,2],[64368,2],[62587,1],[61973,1],[64007,2],[69653,2]]","archetype_id":479,"popularity_delta":1.45,"total_games":612,"win_rate":58.86,"avg_game_length_seconds":433,"avg_num_player_turns":8},{"shortid":"Cuq0DCs35zH7ck9kIT6Kid","deck_list":"[[59594,2],[62926,2],[69705,2],[64711,1],[64729,1],[62947,2],[63323,2],[61187,2],[56444,1],[62927,2],[64008,2],[57546,2],[62993,1],[64368,2],[62924,2],[62587,1],[61973,1],[61189,2]]","archetype_id":15,"popularity_delta":0.97,"total_games":420,"win_rate":60.88,"avg_game_length_seconds":410,"avg_num_player_turns":7.5},{"shortid":"P1u7Yuh1znBAGFKSD1qGNc","deck_list":"[[62583,2],[66856,1],[62926,2],[56445,2],[56554,2],[64729,1],[63323,2],[61187,2],[56444,1],[62927,2],[56555,2],[56556,2],[57546,2],[59584,1],[62993,1],[62924,2],[64368,2],[62587,1]]","archetype_id":15,"popularity_delta":0.74,"total_games":406,"win_rate":59.97,"avg_game_length_seconds":525,"avg_num_player_turns":9.5}],"PRIEST":[{"shortid":"sBJkBMovbAP6tVqaBosm3f","deck_list":"[[61639,2],[62584,2],[61685,2],[66856,1],[61945,1],[61944,1],[64711,1],[56624,2],[61308,1],[57160,1],[64729,1],[64443,1],[61283,2],[62874,2],[61674,2],[61435,2],[64713,2],[59223,2],[61268,2]]","archetype_id":36,"popularity_delta":1.84,"total_games":301,"win_rate":54.54,"avg_game_length_seconds":488,"avg_num_player_turns":9},{"shortid":"rbx91LsrYu1rOtHaDpfQIh","deck_list":"[[62584,2],[69707,2],[66856,1],[64720,1],[61944,2],[63188,1],[56595,2],[57160,1],[62486,2],[66861,1],[59918,2],[63821,2],[62873,2],[62878,2],[62874,2],[64716,1],[64349,1],[63398,1],[64713,2]]","archetype_id":56,"popularity_delta":0.49,"total_games":132,"win_rate":52.86,"avg_game_length_seconds":583,"avg_num_player_turns":10.5},{"shortid":"7UE3NPUB4lFQtxNAfzxPVe","deck_list":"[[59579,2],[59599,2],[61898,2],[64429,2],[56624,2],[69723,2],[59035,2],[64010,2],[64443,1],[69615,2],[64419,2],[59590,2],[59623,1],[57182,2],[60043,2],[59223,2]]","archetype_id":484,"popularity_delta":0.34,"total_games":135,"win_rate":54.07,"avg_game_length_seconds":347,"avg_num_player_turns":6.5}],"ROGUE":[{"shortid":"MPd4jRau3NRvhWrGD8IQEg","deck_list":"[[64033,2],[56377,2],[62890,2],[61159,2],[56527,2],[64711,1],[64034,2],[61151,2],[64678,1],[58794,2],[64031,2],[69622,2],[64163,2],[69621,2],[60043,2],[64166,2]]","archetype_id":155,"popularity_delta":0.73,"total_games":234,"win_rate":48.2,"avg_game_length_seconds":460,"avg_num_player_turns":8},{"shortid":"p6da3QTy8zd6m3pqUOemNb","deck_list":"[[64033,2],[62890,2],[61159,2],[56527,2],[64711,1],[59914,2],[64034,2],[61635,1],[61151,1],[64678,1],[58794,2],[64031,2],[61171,2],[69622,2],[64163,2],[69621,2],[64166,2]]","archetype_id":155,"popularity_delta":0.57,"total_games":509,"win_rate":54.19,"avg_game_length_seconds":481,"avg_num_player_turns":8},{"shortid":"1lygGbJkMvAJ1XKRvRAE6","deck_list":"[[59029,2],[61159,2],[63591,1],[59039,1],[63358,2],[61151,2],[58794,2],[64014,2],[62891,2],[61171,2],[69622,2],[62888,2],[59556,2],[57182,2],[57184,2],[60043,2]]","archetype_id":487,"popularity_delta":0.4,"total_games":151,"win_rate":40.78,"avg_game_length_seconds":440,"avg_num_player_turns":7}],"SHAMAN":[{"shortid":"DoAnDdtP12wDYVZnimWhJc","deck_list":"[[64214,1],[64320,2],[56411,2],[61227,2],[61580,2],[64321,2],[63279,2],[61226,2],[59164,1],[63073,2],[63331,2],[69632,1],[63277,2],[69516,2],[63072,2],[69731,1],[69625,2]]","archetype_id":61,"popularity_delta":1.18,"total_games":1173,"win_rate":59.62,"avg_game_length_seconds":407,"avg_num_player_turns":7.5},{"shortid":"WM0JW2A0UjdFq1EyWpfKOh","deck_list":"[[56411,2],[61580,2],[61226,2],[63073,2],[61224,2],[61223,2],[69630,2],[63331,2],[63277,2],[69516,2],[69517,2],[56467,2],[63072,2],[56472,2],[69625,2]]","archetype_id":469,"popularity_delta":0.98,"total_games":2033,"win_rate":58.27,"avg_game_length_seconds":374,"avg_num_player_turns":7},{"shortid":"lSSZcLcP0Agc0LvLdqj7pf","deck_list":"[[64214,2],[64320,2],[56411,2],[61227,2],[61580,2],[64321,2],[63279,1],[61226,2],[63073,2],[63331,2],[69632,1],[63277,2],[69516,2],[63072,2],[69731,2],[69625,2]]","archetype_id":61,"popularity_delta":0.3,"total_games":572,"win_rate":59.3,"avg_game_length_seconds":401,"avg_num_player_turns":7.5},{"shortid":"wHT0TPkKwLQ6sh0tPkgWNc","deck_list":"[[56411,2],[64320,2],[61227,2],[61580,2],[64321,2],[63279,2],[61226,2],[59164,1],[63073,2],[63331,2],[69632,1],[63277,2],[69516,2],[63072,2],[69731,2],[69625,2]]","archetype_id":61,"popularity_delta":0.3,"total_games":590,"win_rate":58.32,"avg_game_length_seconds":401,"avg_num_player_turns":7.5},{"shortid":"3ypiFzKjNetYc2Yh5cLhtg","deck_list":"[[63098,2],[56411,2],[69626,2],[61962,2],[58977,2],[64321,2],[66288,2],[64356,2],[59164,1],[60016,2],[63331,2],[62442,2],[61961,2],[59213,2],[64322,1],[69625,2]]","archetype_id":306,"popularity_delta":0.3,"total_games":895,"win_rate":56.98,"avg_game_length_seconds":508,"avg_num_player_turns":8.5}],"WARLOCK":[{"shortid":"T5IUjSNWhHXY8pwoZ7NvF","deck_list":"[[61203,1],[64893,2],[61971,2],[69735,2],[64900,1],[59035,2],[63368,2],[64899,2],[63218,1],[59585,2],[63216,2],[60043,2],[69636,2],[56502,2],[59223,2],[56501,2],[64714,1]]","archetype_id":498,"popularity_delta":9.98,"total_games":2367,"win_rate":45.95,"avg_game_length_seconds":430,"avg_num_player_turns":7.5},{"shortid":"zPztTQiuxDrqcOXZ989OSf","deck_list":"[[64704,1],[61971,2],[69735,2],[64900,1],[64711,1],[59035,2],[63368,2],[63217,2],[64710,2],[64899,2],[64903,1],[69553,1],[63218,1],[63192,2],[59585,2],[63216,2],[60043,2],[59223,2]]","archetype_id":307,"popularity_delta":0.31,"total_games":1701,"win_rate":56.36,"avg_game_length_seconds":468,"avg_num_player_turns":8},{"shortid":"3ksKwPWnZ1a2YgV8Z7WfXd","deck_list":"[[64704,1],[61971,2],[64900,1],[69735,2],[64711,1],[59035,2],[63368,2],[63217,2],[64710,2],[64899,2],[69553,2],[63192,2],[63218,1],[59585,2],[63216,2],[60043,2],[59223,2]]","archetype_id":307,"popularity_delta":0.26,"total_games":70,"win_rate":55.42,"avg_game_length_seconds":496,"avg_num_player_turns":8.5}],"WARRIOR":[{"shortid":"yRfha5rtBpaGiYovaxBPgd","deck_list":"[[58979,2],[64280,1],[63701,2],[61237,2],[69677,2],[62462,2],[65656,2],[69679,2],[63125,1],[64279,2],[64277,2],[60023,2],[66854,2],[61249,2],[64278,2],[64975,2]]","archetype_id":162,"popularity_delta":0.92,"total_games":2017,"win_rate":55.19,"avg_game_length_seconds":461,"avg_num_player_turns":8.5},{"shortid":"WdTsmLySLoWUlVLC6L9iCe","deck_list":"[[63119,2],[64720,1],[64280,1],[63701,2],[61237,2],[63118,1],[62462,2],[65656,1],[69679,2],[58978,1],[64279,2],[64277,2],[66854,2],[61238,2],[60023,1],[64278,2],[63398,1],[59411,1],[64975,2]]","archetype_id":162,"popularity_delta":0.91,"total_games":757,"win_rate":55.65,"avg_game_length_seconds":485,"avg_num_player_turns":9},{"shortid":"dYezmiWdpTGQoutYs1Qhcd","deck_list":"[[63119,2],[64280,1],[63701,2],[61237,2],[63118,1],[69677,2],[62462,2],[57718,1],[69679,2],[63125,1],[58978,2],[64279,2],[64277,2],[66854,2],[60023,1],[64278,2],[59411,1],[64975,2]]","archetype_id":162,"popularity_delta":0.88,"total_games":1034,"win_rate":54.84,"avg_game_length_seconds":482,"avg_num_player_turns":9}]}},"as_of":"2021-09-28T21:50:13Z"}